{
  "date": "2026-05-19",
  "type": "us",
  "label": "🇺🇸 미국 시장 브리핑",
  "title": "긴급 점검: 금리 1년 최고·반도체 매도세 경보",
  "direction": "하락 우위",
  "up_pct": 30,
  "confidence": 74,
  "reasons": [
    "📉 오늘 미국 증시가 약하게 시작할 것 같아요. S&P500 선물이 -0.44%, 나스닥 선물이 -0.78%로 프리마켓이 전반적으로 내려가 있거든요.",
    "🏦 채권 시장이 주식에 부담을 주고 있어요. 미국채 10년물이 4.623%(+2.8bp)로 1년 만에 최고치 수준까지 올라왔거든요. 금리가 높아지면 기술주 같은 성장주의 밸류에이션(적정 주가 계산)이 낮아져서 매도세를 자극할 수 있어요.",
    "💡 반도체 섹터에서 강한 매도세가 나오고 있어요. 메모리 반도체 ETF(DRAM)가 -3.48% 급락했고, MU(마이크론)은 -5.95%, AMAT(어플라이드 머티어리얼즈)도 -5.28% 하락했어요. 반도체가 지수 전체를 끌어내리는 상황이에요."
  ],
  "link": "https://doubleshot.space/briefings/2026-05-19/",
  "updated_at": "2026-05-19 21:16 KST"
}